Metadata-Version: 2.1
Name: gouhan
Version: 5.2.0
Summary: This is a test
Home-page: https://upload.pypi.org/legacy
Author: zhu
Author-email: 15010232321@163.com
License: UNKNOWN
Platform: UNKNOWN
Classifier: Programming Language :: Python :: 3
License-File: LICENSE
